screening_ai/__init__.py
screening_ai/api_client.py
screening_ai/api_response.py
screening_ai/configuration.py
screening_ai/exceptions.py
screening_ai/py.typed
screening_ai/rest.py
screening_ai/screening.py
screening_ai/api/__init__.py
screening_ai/api/platform_screening_jobs_api.py
screening_ai/api/platform_screening_submissions_api.py
screening_ai/api/platform_screening_templates_api.py
screening_ai/models/__init__.py
screening_ai/models/api_response_wrapper.py
screening_ai/models/api_response_wrapper_data.py
screening_ai/models/create_platform_organisation_billing_stripe_session_response_dto.py
screening_ai/models/create_platform_screening_form_submission_dto.py
screening_ai/models/create_platform_screening_submission_response_dto.py
screening_ai/models/create_platform_screening_submission_streaming_room_token_dto.py
screening_ai/models/create_screening_template_dto.py
screening_ai/models/generate_screening_template_questions_dto.py
screening_ai/models/get_all_organisation_member_status_of_org_list_response_dto.py
screening_ai/models/get_all_platform_screening_templates_of_org_response_dto.py
screening_ai/models/get_organisation_billing_via_org_id_response_dto.py
screening_ai/models/get_organisation_member_status_response_dto.py
screening_ai/models/get_platform_organisation_api_key_response_dto.py
screening_ai/models/get_platform_screening_submissions_of_org_dto.py
screening_ai/models/platform_create_screening_job_dto.py
screening_ai/models/platform_organisation_response_dto.py
screening_ai/models/platform_organisations_list_response_dto.py
screening_ai/models/platform_screening_job_list_response_dto.py
screening_ai/models/platform_screening_job_response_dto.py
screening_ai/models/platform_screening_submission_create_stream_room_response_dto.py
screening_ai/models/platform_screening_submission_list_response_dto.py
screening_ai/models/platform_screening_submission_response_dto.py
screening_ai/models/platform_screening_submission_text_from_audio_response_dto.py
screening_ai-1.0.1.dist-info/LICENSE
screening_ai-1.0.1.dist-info/METADATA
screening_ai-1.0.1.dist-info/WHEEL
screening_ai-1.0.1.dist-info/top_level.txt
screening_ai-1.0.1.dist-info/RECORD
