Metadata-Version: 2.2
Name: screening-ai
Version: 1.0.1
Summary: Screening AI API Docs
Home-page: https://github.com/Resumepal/screening_ai_python
Author: ByteRaven
Author-email: akshit@byteraven.ai
Keywords: OpenAPI,OpenAPI-Generator,Screening AI API Docs
License-File: LICENSE
Requires-Dist: urllib3<3.0.0,>=1.25.3
Requires-Dist: python-dateutil>=2.8.2
Requires-Dist: pydantic>=2
Requires-Dist: typing-extensions>=4.7.1
Dynamic: author
Dynamic: author-email
Dynamic: description
Dynamic: description-content-type
Dynamic: home-page
Dynamic: keywords
Dynamic: requires-dist
Dynamic: summary
